wmi_client_wrapper/__init__.py
wmi_client_wrapper/wrapper.py
wmi_client_wrapper_py3-2023.1.data/data/README.md
wmi_client_wrapper_py3-2023.1.dist-info/LICENSE
wmi_client_wrapper_py3-2023.1.dist-info/METADATA
wmi_client_wrapper_py3-2023.1.dist-info/WHEEL
wmi_client_wrapper_py3-2023.1.dist-info/top_level.txt
wmi_client_wrapper_py3-2023.1.dist-info/RECORD
