Metadata-Version: 2.1
Name: wmi-client-wrapper-py3
Version: 2023.1
Summary: A fork of Bryan Bishop's wmi-client-wrapper extended to include Python3 support
Home-page: https://github.com/ftpsolutions/python-wmi-client-wrapper
Author: Edward Beech
Author-email: edward.beech@ftpsolutions.com.au
License: BSD
Keywords: sample setuptools development
Classifier: Development Status :: 3 - Alpha
Classifier: Intended Audience :: Developers
Classifier: Topic :: Software Development :: Libraries
Classifier: License :: OSI Approved :: BSD License
Classifier: Programming Language :: Python :: 2.7
Classifier: Programming Language :: Python :: 3.6
License-File: LICENSE
Requires-Dist: mock (==2.0.0)
Requires-Dist: sh (==1.12.14)
Requires-Dist: future (==0.18.3)
Provides-Extra: dev
Requires-Dist: check-manifest ; extra == 'dev'
Provides-Extra: test
Requires-Dist: coverage ; extra == 'test'
